{
  "name": "Blanche Byrd",
  "age": 43,
  "address": {
    "street": "Honobo Place",
    "city": "Joudumo",
    "state": "DC",
    "zip": "60196"
  },
  "contact": {
    "phone": "(247) 908-4791",
    "servicePhone": "800295911"
  },
  "birthday": "1980-06-04T05:06:44.607Z",
  "ip": "77.202.168.241",
  "foo": "bar",
  "profile": {
    "about": "Ah ke zagsig ahpuvawo gupepo simefma guskik ropca ruzolhu zuunuvap ta owposo im. Egaku lelpegen nizveako cer uluifmu viv appek fag vocsun zofej nezoh gutfo dadi kewfenbab. Vaohozi pilkawpi gizir aba ub folfowuz fub rectahmeh fegdazi ot na daf siijoco dimlu fibsajda temo. Ze acamula tuatodon coho go gowadvob mulanu uwi osoipi nazpilme fepmojfif afsutiz. Celaogo mehogane vuzrenlu ritpozub mova he vanse vucet foibadof mirtojjom ekgijab op gical kire. Gumnansir pewu siodris ipfuvvah apugip mejhorec renefa teku wuuk kivujkid wiufiju pul.",
    "bio": "Op magapja wur ezret licos tuzzuuh malobalu ad wavuok piwduz rurezom sagecu ohu ugirok legu majdojihu. Ipmol sa kuijeve hugo wabmovah bavbagcil dedirmo ozepo jubokcu du zifgan zepej. Giruglig lupmu cejac parja te uwebecren visevi hacduaje umu ovone nuv vi efkona ru de heruk tazrol. Pawuc baw papveede le buplez ri bavipamo zefpira poaf vo cihlej jozetza megreiko. Zesojove omaresmu emegircib gub rulpabun unicofun ozulaak codi guvlu hib ke asape wimiv. Bo tubrorbom eka lunir upbi ke joc ufjara buj tu bugotid ves forujfur wa ipojag. Jikadri igwiva hu zedmop asme pihuted ormu ew zeh pid osa tih."
  },
  "apiKey": "7b380815b6522e3ce7b53106c776e25f62dcde92c96e776a3c3245dea700d571",
  "currency": {
    "code": "TVD",
    "name": "Tuvalu Dollar"
  }
}