{
  "name": "Clayton Collier",
  "age": 56,
  "address": {
    "street": "Bulro Point",
    "city": "Jibaena",
    "state": "TX",
    "zip": "68810"
  },
  "contact": {
    "phone": "(362) 332-3066",
    "servicePhone": "800788724"
  },
  "birthday": "1973-01-11T05:01:57.674Z",
  "ip": "141.189.216.21",
  "foo": "bar",
  "profile": {
    "about": "Minnu nicoftil irire nasa ri gevjun hak ubuakoja urouba finnu vi mijewe. Tu uvuviw inbev ir kez dahis haket relen duh mokgop toh bac juwupov si. Upvaam ma duztuk fafon rujudo nemiewo tawhal lukha eromukupu me mi sujrukot jolzufpes.",
    "bio": "Ohilaf mud di pudozi ukona ewe gesivuavi bowiti suvevza wuzpizak segoh je fufjupka feznepra za pa. Ozgegap zafizega vi geb tedothe nuj temlep jil fobil uri bujwem lasbu mor. Ucufisge ufo hacca pos nube zojavu ugikoc caparfih ez picsuv ade litilaced pojno. Bosju otakorpo fana wop we jih ip tivbap deto ihoimu jotojod wig curuh. Sacgu fegneza fuf izhas ugum matojzum neet gaowjus uthimsuv rum dovbo jasapi waw raohu fufdodcun nowopeoc vavog. Mikze difzac hafej ovalepcor heba gohom mac ev ugagodel woja nahahhul zigigir vuotomej buk duudgem suteniz bu."
  },
  "apiKey": "c9ba6ba9f9bb18fb4b7e1daa937eb20207872b3122a3b2cb57638e3475351b62",
  "currency": {
    "code": "BDT",
    "name": "Bangladesh Taka"
  }
}