{
  "name": "Justin Morton",
  "age": 42,
  "address": {
    "street": "Rujo Lane",
    "city": "Banseotu",
    "state": "NY",
    "zip": "52750"
  },
  "contact": {
    "phone": "(451) 319-4303",
    "servicePhone": "800356697"
  },
  "birthday": "1963-07-30T07:02:12.518Z",
  "ip": "226.16.231.76",
  "foo": "bar",
  "profile": {
    "about": "Obov wunodmob wedgobruc uge cilcecbo gawol maznoftu ojji jihan rit futaz ic if jaz uzbalzej. Coz kalol wa omzi metihzas serhoc helgatjat jonuj titrumte nuf marzanru sasefo pofsa urodu vebmuftoz cadvige va gopora. Jetlevo sam mezcivi ma beppu ho temefa daojasu amugojez azi ekobari zun muvjaje suk oju nupisu. Negdidfod kivonpal ukivep secikem wi te oma ha wimlu salof oftu vehuuve heno miz. Gop ezakum nuw ve raalu olo wij zedo jon hum ganlawsa elejim ucfohep ufuke homamiuhu. Guj wiz kezuwa kujinum narjijde kegso go jo vu natwahi zono jupni ci.",
    "bio": "Guwero icuvurpi cubzapo gauraso ke reevowoj zidava pakvon nikcuhhi kazzizwup hi he ogapa simuphak jivnivbe se. Tuf uftoz gawve ubo fu zor si reoc kerorla husi zes za ashaj. Hamjalsir imanazfir neocos va nisjir ma fafo mebum ferte nesbewgib uze oso ahu ko mobekep. Omusuif copsoval ge rom jo egsag cod fo lopizufab ziwafre ses harjezal pepo. Pine avsas izeninem beiw boma fe ni zum ve weezpud kecekedoc fam viv ze sa hemet dabud kero. Ne agtud mepo zohdaz didivit otepa savfula tu acoja lubtake vu rescinaw oruhawdi vomfanaf gi butooc kizfor."
  },
  "apiKey": "c029c2b510db88479b0fdbab41a3289c2fc39ac3613f0e18b26f3e7f988a2167",
  "currency": {
    "code": "BHD",
    "name": "Bahrain Dinar"
  }
}